hound/__init__.py
hound/client.py
hound/snowflake.py
hound-1.0.1.dist-info/LICENSE
hound-1.0.1.dist-info/METADATA
hound-1.0.1.dist-info/WHEEL
hound-1.0.1.dist-info/top_level.txt
hound-1.0.1.dist-info/RECORD
