Metadata-Version: 2.1
Name: hound
Version: 1.0.1
Summary: A FireCloud database extension
Home-page: https://github.com/getzlab/hound
Author: Aaron Graubert - Broad Institute - Cancer Genome Computational Analysis - Getz Lab
Author-email: aarong@broadinstitute.org
License: BSD3
Platform: UNKNOWN
Classifier: Development Status :: 4 - Beta
Classifier: Programming Language :: Python :: 3
Classifier: Intended Audience :: Science/Research
Classifier: Topic :: Scientific/Engineering :: Bio-Informatics
Classifier: Topic :: Scientific/Engineering :: Interface Engine/Protocol Translator
Requires-Dist: google-cloud-storage (>=1.20.0)
Requires-Dist: google-auth (>=1.6.3)
